{"cameraMode":{"drawMode":0,"name":"Shaded","section":"Shading Mode"},"sceneLighting":false,"audioPlay":false,"sceneViewState":{"showFog":true,"showMaterialUpdate":false,"showSkybox":false,"showFlares":true,"showImageEffects":true,"showParticleSystems":true},"in2DMode":false,"pivot":{"x":0.25294724106788638,"y":0.15682914853096009,"z":0.20804516971111298},"rotation":{"x":0.21216455101966859,"y":0.6656623482704163,"z":-0.2061394900083542,"w":0.685119092464447},"size":0.2306113839149475,"orthographic":false}